_align_new.cpython-39-darwin.so
qualtrim_new.cpython-39-darwin.so
ultraplex/__init__.py
ultraplex/__main__.py
ultraplex/_align.c
ultraplex/_align_new.c
ultraplex/_align_new.pyx
ultraplex/_version.py
ultraplex/adapters.py
ultraplex/align.py
ultraplex/filters.py
ultraplex/log.py
ultraplex/modifiers.py
ultraplex/parser.py
ultraplex/pipeline.py
ultraplex/qualtrim.c
ultraplex/qualtrim_new.c
ultraplex/qualtrim_new.pyx
ultraplex/report.py
ultraplex/utils.py
ultraplex/version.py
ultraplex-1.2.9.dist-info/LICENSE
ultraplex-1.2.9.dist-info/METADATA
ultraplex-1.2.9.dist-info/WHEEL
ultraplex-1.2.9.dist-info/entry_points.txt
ultraplex-1.2.9.dist-info/top_level.txt
ultraplex-1.2.9.dist-info/RECORD
