Metadata-Version: 2.1
Name: ultraplex
Version: 1.2.9
Summary: fastq demultiplexer
Home-page: https://github.com/ulelab/ultraplex.git
Author: Oscar Wilkins
Author-email: oscar.wilkins@crick.ac.uk
License: MIT
Classifier: License :: OSI Approved :: MIT License
Classifier: Programming Language :: Python :: 3
Classifier: Programming Language :: Python :: 3.6
Requires-Python: >=3.7
License-File: LICENSE
Requires-Dist: dnaio >=0.5.0
Requires-Dist: xopen ~=1.0.0
Requires-Dist: multiprocess ~=0.70.15
Requires-Dist: setuptools-scm
Requires-Dist: cython >0.29.22
